artfinder/__about__.py
artfinder/__init__.py
artfinder/api.py
artfinder/article.py
artfinder/crossref.py
artfinder/crossref_helpers.py
artfinder/dataclasses.py
artfinder/helpers.py
artfinder/http_requests.py
artfinder-0.0.2.dist-info/METADATA
artfinder-0.0.2.dist-info/WHEEL
artfinder-0.0.2.dist-info/licenses/LICENSE.txt
artfinder-0.0.2.dist-info/RECORD
