Metadata-Version: 2.4
Name: artfinder
Version: 0.0.2
Project-URL: Documentation, https://github.com/Kaldarinz/artfinder#readme
Project-URL: Issues, https://github.com/Kaldarinz/artfinder/issues
Project-URL: Source, https://github.com/Kaldarinz/artfinder
Author-email: Anton Popov <a.popov.fizteh@gmail.com>
License-Expression: MIT
License-File: LICENSE.txt
Classifier: Development Status :: 4 - Beta
Classifier: Programming Language :: Python
Classifier: Programming Language :: Python :: 3.10
Classifier: Programming Language :: Python :: 3.11
Classifier: Programming Language :: Python :: 3.12
Classifier: Programming Language :: Python :: Implementation :: CPython
Classifier: Programming Language :: Python :: Implementation :: PyPy
Requires-Python: >=3.10
Requires-Dist: aiohttp
Requires-Dist: pandas
Requires-Dist: requests
